pybokio/__init__.py
pybokio/_routers/__init__.py
pybokio/_routers/account_routers.py
pybokio/_routers/accounting_routers.py
pybokio/_routers/base_router.py
pybokio/_utils/__init__.py
pybokio/_utils/verification.py
pybokio/client/__init__.py
pybokio/client/_base_client.py
pybokio/client/bokio_client.py
pybokio/client/_subclients/__init__.py
pybokio/client/_subclients/account_client.py
pybokio/client/_subclients/accounting_client.py
pybokio/exceptions/__init__.py
pybokio/exceptions/_common.py
pybokio/responses/__init__.py
pybokio-0.1.1.dist-info/LICENSE
pybokio-0.1.1.dist-info/METADATA
pybokio-0.1.1.dist-info/WHEEL
pybokio-0.1.1.dist-info/top_level.txt
pybokio-0.1.1.dist-info/RECORD
