Metadata-Version: 2.1
Name: pybokio
Version: 0.1.1
Summary: Unofficial SDK for interacting with Bokio.
Home-page: https://github.com/vonNiklasson/pybokio
Author: Johan Niklasson
Author-email: johan@niklasson.me
License: MIT
Project-URL: Source, https://github.com/vonNiklasson/pybokio
Project-URL: Bug Reports, https://github.com/vonNiklasson/pybokio/issues
Keywords: SDK API Bokio
Platform: UNKNOWN
Classifier: Development Status :: 3 - Alpha
Classifier: License :: OSI Approved :: MIT License
Classifier: Intended Audience :: Developers
Classifier: Operating System :: OS Independent
Classifier: Programming Language :: Python :: 3
Classifier: Programming Language :: Python :: 3.6
Classifier: Programming Language :: Python :: 3.7
Classifier: Programming Language :: Python :: 3.8
Classifier: Programming Language :: Python :: 3.9
Classifier: Programming Language :: Python :: 3 :: Only
Classifier: Topic :: Software Development
Classifier: Topic :: Office/Business :: Financial :: Accounting
Requires-Python: >=3.6
Requires-Dist: requests (<3,>=2.20)
Requires-Dist: jsonschema (<4,>=3.0)
Requires-Dist: dataclasses (==0.8) ; python_version >= "3.6" and python_version < "3.7"
